describr/__init__.py
describr/describr.py
describr-0.0.31.dist-info/METADATA
describr-0.0.31.dist-info/WHEEL
describr-0.0.31.dist-info/top_level.txt
describr-0.0.31.dist-info/RECORD
