Metadata-Version: 2.1
Name: describr
Version: 0.0.31
Summary: Describr is a Python library that provides a convenient way to generate descriptive statistics for datasets.
Home-page: https://github.com/famutimine/describr
Author: Daniel Famutimi MD, MPH
Author-email: danielfamutimi@gmail.com
License: MIT
Keywords: descriptive statistics
Classifier: Development Status :: 5 - Production/Stable
Classifier: Intended Audience :: Developers
Classifier: Intended Audience :: Healthcare Industry
Classifier: Intended Audience :: System Administrators
Classifier: License :: OSI Approved :: MIT License
Classifier: Programming Language :: Python :: 3
Classifier: Programming Language :: Python :: 3.6
Classifier: Programming Language :: Python :: 3.7
Classifier: Programming Language :: Python :: 3.8
Classifier: Programming Language :: Python :: 3.9
Classifier: Topic :: Software Development :: Libraries :: Python Modules
Classifier: Topic :: Scientific/Engineering :: Mathematics
Classifier: Topic :: Scientific/Engineering :: Information Analysis
Requires-Dist: numpy
Requires-Dist: pandas
Requires-Dist: scipy
